awesomeversion/__init__.py
awesomeversion/awesomeversion.py
awesomeversion/comparehandlers/__init__.py
awesomeversion/comparehandlers/container.py
awesomeversion/comparehandlers/modifier.py
awesomeversion/comparehandlers/sections.py
awesomeversion/comparehandlers/simple.py
awesomeversion/exceptions.py
awesomeversion/py.typed
awesomeversion/strategy.py
awesomeversion/typing.py
awesomeversion/utils/__init__.py
awesomeversion/utils/regex.py
awesomeversion/utils/validate.py
awesomeversion-25.5.0.dist-info/LICENCE.md
awesomeversion-25.5.0.dist-info/METADATA
awesomeversion-25.5.0.dist-info/WHEEL
awesomeversion-25.5.0.dist-info/RECORD
