Metadata-Version: 2.3
Name: awesomeversion
Version: 25.5.0
Summary: One version package to rule them all, One version package to find them, One version package to bring them all, and in the darkness bind them.
License: MIT
Keywords: calver,semver,0ver,version,pep440,buildver
Author: Ludeeus
Author-email: ludeeus@ludeeus.dev
Maintainer: Ludeeus
Maintainer-email: ludeeus@ludeeus.dev
Requires-Python: >=3.9,<4.0
Classifier: Intended Audience :: Developers
Classifier: License :: OSI Approved :: MIT License
Classifier: Natural Language :: English
Classifier: Programming Language :: Python :: 3
Classifier: Programming Language :: Python :: 3.9
Classifier: Programming Language :: Python :: 3.10
Classifier: Programming Language :: Python :: 3.11
Classifier: Programming Language :: Python :: 3.12
Classifier: Programming Language :: Python :: 3.13
Classifier: Topic :: Software Development :: Libraries :: Python Modules
Project-URL: Repository, https://github.com/ludeeus/awesomeversion
